{"is_source_file": true, "format": "C++ header", "description": "This file is a C++ header file from Google Test's internal implementation, containing declarations, macros, and utility classes used internally by the framework.", "external_files": ["gtest/internal/gtest-port.h", "gtest/internal/gtest-filepath.h", "gtest/internal/gtest-string.h", "gtest/internal/gtest-type-util.h"], "external_methods": [], "published": ["testing::AssertionResult", "testing::Message", "testing::Test", "testing::internal::PrintToString", "testing::internal::EqFailure", "testing::internal::GetTypeId", "testing::internal::MakeAndRegisterTestInfo", "testing::internal::SkipPrefix"], "classes": [{"name": "AssertionResult", "description": "Represents the result of an assertion, indicating success or failure."}, {"name": "Message", "description": "Represents a message generated by Google Test, used for failure messages."}, {"name": "Test", "description": "Represents a test case within Google Test framework."}, {"name": "FloatingPoint<RawType>", "description": "A template class for comparing floating-point numbers with ULP precision."}, {"name": "TypeIdHelper<T>", "description": "Helper class to generate unique IDs for types."}, {"name": "TestFactoryBase", "description": "Abstract base class for creating test instances."}, {"name": "TestFactoryImpl<TestClass>", "description": "Template implementation of TestFactoryBase for specific test classes."}, {"name": "CodeLocation", "description": "Stores source code location info (file and line number)."}, {"name": "NativeArray<Element>", "description": "Adapts native arrays for testing, supporting reference and copy semantics."}], "methods": [{"name": "AppendUserMessage", "description": "Appends a user message to a Google Test-generated message."}, {"name": "ReinterpretBits", "description": "Reinterprets bits as a floating point number for comparison."}, {"name": "Equals", "description": "Various functions to compare arrays or ranges of elements."}, {"name": "MakeAndRegisterTestInfo", "description": "Creates and registers a new test info object within Google Test."}, {"name": "SkipPrefix", "description": "Skips prefix string in given input if present."}, {"name": "bool AddTestName(const char * file,int line,const char * case_name,const char * test_name)", "scope": "testing::internal::TypedTestSuitePState", "scopeKind": "class", "description": "unavailable"}, {"name": "bool AlmostEquals(const FloatingPoint & rhs) const", "scope": "testing::internal::FloatingPoint", "scopeKind": "class", "description": "unavailable"}, {"name": "bool AlwaysFalse()", "scope": "testing::internal", "scopeKind": "namespace", "description": "unavailable"}, {"name": "decltype(std::forward<F> (f)(this->Get<Idx> ()...)) Apply(F && f)", "scope": "testing::internal::FlatTupleBase", "scopeKind": "struct", "description": "unavailable"}, {"name": "decltype(std::forward<F> (f)(this->Get<Idx> ()...)) Apply(F && f) const", "scope": "testing::internal::FlatTupleBase", "scopeKind": "struct", "description": "unavailable"}, {"name": "bool ArrayEq(const T * lhs,size_t size,const U * rhs)", "scope": "testing::internal", "scopeKind": "namespace", "description": "unavailable"}, {"name": "bool ArrayEq(const T (& lhs)[N],const U (& rhs)[N])", "scope": "testing::internal", "scopeKind": "namespace", "description": "unavailable"}, {"name": "bool ArrayEq(const T & lhs,const U & rhs)", "scope": "testing::internal", "scopeKind": "namespace", "description": "unavailable"}, {"name": "CodeLocation(const std::string & a_file,int a_line)", "scope": "testing::internal::CodeLocation", "scopeKind": "struct", "description": "unavailable"}, {"name": "ConstCharPtr(const char * str)", "scope": "testing::internal::ConstCharPtr", "scopeKind": "struct", "description": "unavailable"}, {"name": "void CopyArray(const T (& from)[N],U (* to)[N])", "scope": "testing::internal", "scopeKind": "namespace", "description": "unavailable"}, {"name": "void CopyArray(const T & from,U * to)", "scope": "testing::internal", "scopeKind": "namespace", "description": "unavailable"}, {"name": "void CopyArray(const T * from,size_t size,U * to)", "scope": "testing::internal", "scopeKind": "namespace", "description": "unavailable"}, {"name": "Test * CreateTest()", "scope": "testing::internal::TestFactoryImpl", "scopeKind": "class", "description": "unavailable"}, {"name": "Bits DistanceBetweenSignAndMagnitudeNumbers(const Bits & sam1,const Bits & sam2)", "scope": "testing::internal::FloatingPoint", "scopeKind": "class", "description": "unavailable"}, {"name": "FlatTuple(FlatTupleConstructTag tag,Args &&...args)", "scope": "testing::internal::FlatTuple", "scopeKind": "class", "description": "unavailable"}, {"name": "FlatTupleBase(FlatTupleConstructTag,Args &&...args)", "scope": "testing::internal::FlatTupleBase", "scopeKind": "struct", "description": "unavailable"}, {"name": "FlatTupleElemBase(FlatTupleConstructTag,Arg && t)", "scope": "testing::internal::FlatTupleElemBase", "scopeKind": "struct", "description": "unavailable"}, {"name": "FloatingPoint(const RawType & x)", "scope": "testing::internal::FloatingPoint", "scopeKind": "class", "description": "unavailable"}, {"name": "GTEST_DISABLE_MSC_WARNINGS_POP_() const", "scope": "testing::internal", "scopeKind": "namespace", "description": "unavailable"}, {"name": "std::vector<std::string> GenerateNames()", "scope": "testing::internal", "scopeKind": "namespace", "description": "unavailable"}, {"name": "void GenerateNamesRecursively(Types,std::vector<std::string> * result,int i)", "scope": "testing::internal", "scopeKind": "namespace", "description": "unavailable"}, {"name": "void GenerateNamesRecursively(internal::None,std::vector<std::string> *,int)", "scope": "testing::internal", "scopeKind": "namespace", "description": "unavailable"}, {"name": "const typename ElemFromList<I,T...>::type & Get() const", "scope": "testing::internal::FlatTupleBase", "scopeKind": "struct", "description": "unavailable"}, {"name": "ElemFromList<I,T...>::type & Get()", "scope": "testing::internal::FlatTupleBase", "scopeKind": "struct", "description": "unavailable"}, {"name": "const CodeLocation & GetCodeLocation(const std::string & test_name) const", "scope": "testing::internal::TypedTestSuitePState", "scopeKind": "class", "description": "unavailable"}, {"name": "std::string GetName(int i)", "scope": "testing::internal::DefaultNameGenerator", "scopeKind": "struct", "description": "unavailable"}, {"name": "SetUpTearDownSuiteFuncType GetNotDefaultOrNull(SetUpTearDownSuiteFuncType a,SetUpTearDownSuiteFuncType def)", "scope": "testing::internal", "scopeKind": "namespace", "description": "unavailable"}, {"name": "std::string GetPrefixUntilComma(const char * str)", "scope": "testing::internal", "scopeKind": "namespace", "description": "unavailable"}, {"name": "SetUpTearDownSuiteFuncType GetSetUpCaseOrSuite(const char * filename,int line_num)", "scope": "testing::internal::SuiteApiResolver", "scopeKind": "struct", "description": "unavailable"}, {"name": "SetUpTearDownSuiteFuncType GetTearDownCaseOrSuite(const char * filename,int line_num)", "scope": "testing::internal::SuiteApiResolver", "scopeKind": "struct", "description": "unavailable"}], "calls": ["testing::internal::ArrayEq", "testing::internal::CopyArray", "testing::internal::GetTypeId", "testing::internal::MakeAndRegisterTestInfo"], "search-terms": ["gtest/internal/gtest-internal.h", "FloatingPoint comparison", "Google Test internal declarations", "test registration functions", "internal macros and classes"], "state": 2, "file_id": 247, "knowledge_revision": 606, "git_revision": "", "ctags": [{"_type": "tag", "name": "AddTestName", "path": "/home/kavia/workspace/code-generation/offline-to-do-list-manager-148807-148823/native_app/build/_deps/googletest-src/googletest/include/gtest/internal/gtest-internal.h", "pattern": "/^  bool AddTestName(const char* file, int line, const char* case_name,$/", "language": "C++", "typeref": "typename:bool", "kind": "function", "signature": "(const char * file,int line,const char * case_name,const char * test_name)", "scope": "testing::internal::TypedTestSuitePState", "scopeKind": "class"}, {"_type": "tag", "name": "AlmostEquals", "path": "/home/kavia/workspace/code-generation/offline-to-do-list-manager-148807-148823/native_app/build/_deps/googletest-src/googletest/include/gtest/internal/gtest-internal.h", "pattern": "/^  bool AlmostEquals(const FloatingPoint& rhs) const {$/", "language": "C++", "typeref": "typename:bool", "kind": "function", "signature": "(const FloatingPoint & rhs) const", "scope": "testing::internal::FloatingPoint", "scopeKind": "class"}, {"_type": "tag", "name": "AlwaysFalse", "path": "/home/kavia/workspace/code-generation/offline-to-do-list-manager-148807-148823/native_app/build/_deps/googletest-src/googletest/include/gtest/internal/gtest-internal.h", "pattern": "/^inline bool AlwaysFalse() { return !AlwaysTrue(); }$/", "language": "C++", "typeref": "typename:bool", "kind": "function", "signature": "()", "scope": "testing::internal", "scopeKind": "namespace"}, {"_type": "tag", "name": "Apply", "path": "/home/kavia/workspace/code-generation/offline-to-do-list-manager-148807-148823/native_app/build/_deps/googletest-src/googletest/include/gtest/internal/gtest-internal.h", "pattern": "/^  auto Apply(F&& f) -> decltype(std::forward<F>(f)(this->Get<Idx>()...)) {$/", "language": "C++", "typeref": "typename:decltype(std::forward<F> (f)(this->Get<Idx> ()...))", "kind": "function", "signature": "(F && f)", "scope": "testing::internal::FlatTupleBase", "scopeKind": "struct"}, {"_type": "tag", "name": "Apply", "path": "/home/kavia/workspace/code-generation/offline-to-do-list-manager-148807-148823/native_app/build/_deps/googletest-src/googletest/include/gtest/internal/gtest-internal.h", "pattern": "/^  auto Apply(F&& f) const -> decltype(std::forward<F>(f)(this->Get<Idx>()...)) {$/", "language": "C++", "typeref": "typename:decltype(std::forward<F> (f)(this->Get<Idx> ()...))", "kind": "function", "signature": "(F && f) const", "scope": "testing::internal::FlatTupleBase", "scopeKind": "struct"}, {"_type": "tag", "name": "ArrayEq", "path": "/home/kavia/workspace/code-generation/offline-to-do-list-manager-148807-148823/native_app/build/_deps/googletest-src/googletest/include/gtest/internal/gtest-internal.h", "pattern": "/^bool ArrayEq(const T* lhs, size_t size, const U* rhs) {$/", "language": "C++", "typeref": "typename:bool", "kind": "function", "signature": "(const T * lhs,size_t size,const U * rhs)", "scope": "testing::internal", "scopeKind": "namespace"}, {"_type": "tag", "name": "ArrayEq", "path": "/home/kavia/workspace/code-generation/offline-to-do-list-manager-148807-148823/native_app/build/_deps/googletest-src/googletest/include/gtest/internal/gtest-internal.h", "pattern": "/^inline bool ArrayEq(const T (&lhs)[N], const U (&rhs)[N]) {$/", "language": "C++", "typeref": "typename:bool", "kind": "function", "signature": "(const T (& lhs)[N],const U (& rhs)[N])", "scope": "testing::internal", "scopeKind": "namespace"}, {"_type": "tag", "name": "ArrayEq", "path": "/home/kavia/workspace/code-generation/offline-to-do-list-manager-148807-148823/native_app/build/_deps/googletest-src/googletest/include/gtest/internal/gtest-internal.h", "pattern": "/^inline bool ArrayEq(const T& lhs, const U& rhs) {$/", "language": "C++", "typeref": "typename:bool", "kind": "function", "signature": "(const T & lhs,const U & rhs)", "scope": "testing::internal", "scopeKind": "namespace"}, {"_type": "tag", "name": "Bits", "path": "/home/kavia/workspace/code-generation/offline-to-do-list-manager-148807-148823/native_app/build/_deps/googletest-src/googletest/include/gtest/internal/gtest-internal.h", "pattern": "/^  typedef typename TypeWithSize<sizeof(RawType)>::UInt Bits;$/", "language": "C++", "kind": "typedef", "scope": "testing::internal::FloatingPoint", "scopeKind": "class"}, {"_type": "tag", "name": "CodeLocation", "path": "/home/kavia/workspace/code-generation/offline-to-do-list-manager-148807-148823/native_app/build/_deps/googletest-src/googletest/include/gtest/internal/gtest-internal.h", "pattern": "/^  CodeLocation(const std::string& a_file, int a_line)$/", "language": "C++", "kind": "function", "signature": "(const std::string & a_file,int a_line)", "scope": "testing::internal::CodeLocation", "scopeKind": "struct"}, {"_type": "tag", "name": "CodeLocation", "path": "/home/kavia/workspace/code-generation/offline-to-do-list-manager-148807-148823/native_app/build/_deps/googletest-src/googletest/include/gtest/internal/gtest-internal.h", "pattern": "/^struct CodeLocation {$/", "language": "C++", "kind": "struct", "scope": "testing::internal", "scopeKind": "namespace"}, {"_type": "tag", "name": "ConstCharPtr", "path": "/home/kavia/workspace/code-generation/offline-to-do-list-manager-148807-148823/native_app/build/_deps/googletest-src/googletest/include/gtest/internal/gtest-internal.h", "pattern": "/^  ConstCharPtr(const char* str) : value(str) {}$/", "language": "C++", "kind": "function", "signature": "(const char * str)", "scope": "testing::internal::ConstCharPtr", "scopeKind": "struct"}, {"_type": "tag", "name": "ConstCharPtr", "path": "/home/kavia/workspace/code-generation/offline-to-do-list-manager-148807-148823/native_app/build/_deps/googletest-src/googletest/include/gtest/internal/gtest-internal.h", "pattern": "/^struct GTEST_API_ ConstCharPtr {$/", "language": "C++", "kind": "struct", "scope": "testing::internal", "scopeKind": "namespace"}, {"_type": "tag", "name": "CopyArray", "path": "/home/kavia/workspace/code-generation/offline-to-do-list-manager-148807-148823/native_app/build/_deps/googletest-src/googletest/include/gtest/internal/gtest-internal.h", "pattern": "/^inline void CopyArray(const T (&from)[N], U (*to)[N]) {$/", "language": "C++", "typeref": "typename:void", "kind": "function", "signature": "(const T (& from)[N],U (* to)[N])", "scope": "testing::internal", "scopeKind": "namespace"}, {"_type": "tag", "name": "CopyArray", "path": "/home/kavia/workspace/code-generation/offline-to-do-list-manager-148807-148823/native_app/build/_deps/googletest-src/googletest/include/gtest/internal/gtest-internal.h", "pattern": "/^inline void CopyArray(const T& from, U* to) {$/", "language": "C++", "typeref": "typename:void", "kind": "function", "signature": "(const T & from,U * to)", "scope": "testing::internal", "scopeKind": "namespace"}, {"_type": "tag", "name": "CopyArray", "path": "/home/kavia/workspace/code-generation/offline-to-do-list-manager-148807-148823/native_app/build/_deps/googletest-src/googletest/include/gtest/internal/gtest-internal.h", "pattern": "/^void CopyArray(const T* from, size_t size, U* to) {$/", "language": "C++", "typeref": "typename:void", "kind": "function", "signature": "(const T * from,size_t size,U * to)", "scope": "testing::internal", "scopeKind": "namespace"}, {"_type": "tag", "name": "CreateTest", "path": "/home/kavia/workspace/code-generation/offline-to-do-list-manager-148807-148823/native_app/build/_deps/googletest-src/googletest/include/gtest/internal/gtest-internal.h", "pattern": "/^  Test* CreateTest() override { return new TestClass; }$/", "language": "C++", "typeref": "typename:Test *", "kind": "function", "signature": "()", "scope": "testing::internal::TestFactoryImpl", "scopeKind": "class"}, {"_type": "tag", "name": "DefaultNameGenerator", "path": "/home/kavia/workspace/code-generation/offline-to-do-list-manager-148807-148823/native_app/build/_deps/googletest-src/googletest/include/gtest/internal/gtest-internal.h", "pattern": "/^struct DefaultNameGenerator {$/", "language": "C++", "kind": "struct", "scope": "testing::internal", "scopeKind": "namespace"}, {"_type": "tag", "name": "DistanceBetweenSignAndMagnitudeNumbers", "path": "/home/kavia/workspace/code-generation/offline-to-do-list-manager-148807-148823/native_app/build/_deps/googletest-src/googletest/include/gtest/internal/gtest-internal.h", "pattern": "/^  static Bits DistanceBetweenSignAndMagnitudeNumbers(const Bits& sam1,$/", "language": "C++", "typeref": "typename:Bits", "kind": "function", "signature": "(const Bits & sam1,const Bits & sam2)", "scope": "testing::internal::FloatingPoint", "scopeKind": "class"}, {"_type": "tag", "name": "Double", "path": "/home/kavia/workspace/code-generation/offline-to-do-list-manager-148807-148823/native_app/build/_deps/googletest-src/googletest/include/gtest/internal/gtest-internal.h", "pattern": "/^typedef FloatingPoint<double> Double;$/", "language": "C++", "typeref": "typename:FloatingPoint<double>", "kind": "typedef", "scope": "testing::internal", "scopeKind": "namespace"}, {"_type": "tag", "name": "DoubleSequence", "path": "/home/kavia/workspace/code-generation/offline-to-do-list-manager-148807-148823/native_app/build/_deps/googletest-src/googletest/include/gtest/internal/gtest-internal.h", "pattern": "/^struct DoubleSequence<false, IndexSequence<I...>, sizeofT> {$/", "language": "C++", "kind": "struct", "scope": "testing::internal", "scopeKind": "namespace"}, {"_type": "tag", "name": "DoubleSequence", "path": "/home/kavia/workspace/code-generation/offline-to-do-list-manager-148807-148823/native_app/build/_deps/googletest-src/googletest/include/gtest/internal/gtest-internal.h", "pattern": "/^struct DoubleSequence<true, IndexSequence<I...>, sizeofT> {$/", "language": "C++", "kind": "struct", "scope": "testing::internal", "scopeKind": "namespace"}, {"_type": "tag", "name": "EditType", "path": "/home/kavia/workspace/code-generation/offline-to-do-list-manager-148807-148823/native_app/build/_deps/googletest-src/googletest/include/gtest/internal/gtest-internal.h", "pattern": "/^enum EditType { kMatch, kAdd, kRemove, kReplace };$/", "language": "C++", "kind": "enum", "scope": "testing::internal::edit_distance", "scopeKind": "namespace"}, {"_type": "tag", "name": "ElemFromList", "path": "/home/kavia/workspace/code-generation/offline-to-do-list-manager-148807-148823/native_app/build/_deps/googletest-src/googletest/include/gtest/internal/gtest-internal.h", "pattern": "/^struct ElemFromList {$/", "language": "C++", "kind": "struct", "scope": "testing::internal", "scopeKind": "namespace"}, {"_type": "tag", "name": "ElemFromListImpl", "path": "/home/kavia/workspace/code-generation/offline-to-do-list-manager-148807-148823/native_app/build/_deps/googletest-src/googletest/include/gtest/internal/gtest-internal.h", "pattern": "/^struct ElemFromListImpl<IndexSequence<I...>> {$/", "language": "C++", "kind": "struct", "scope": "testing::internal", "scopeKind": "namespace"}, {"_type": "tag", "name": "FixtureClass", "path": "/home/kavia/workspace/code-generation/offline-to-do-list-manager-148807-148823/native_app/build/_deps/googletest-src/googletest/include/gtest/internal/gtest-internal.h", "pattern": "/^    typedef Fixture<Type> FixtureClass;$/", "language": "C++", "typeref": "typename:Fixture<Type>", "kind": "typedef", "scope": "testing::internal::TypeParameterizedTest", "scopeKind": "class"}, {"_type": "tag", "name": "FlatTuple", "path": "/home/kavia/workspace/code-generation/offline-to-do-list-manager-148807-148823/native_app/build/_deps/googletest-src/googletest/include/gtest/internal/gtest-internal.h", "pattern": "/^  explicit FlatTuple(FlatTupleConstructTag tag, Args&&... args)$/", "language": "C++", "kind": "function", "signature": "(FlatTupleConstructTag tag,Args &&...args)", "scope": "testing::internal::FlatTuple", "scopeKind": "class"}, {"_type": "tag", "name": "FlatTuple", "path": "/home/kavia/workspace/code-generation/offline-to-do-list-manager-148807-148823/native_app/build/_deps/googletest-src/googletest/include/gtest/internal/gtest-internal.h", "pattern": "/^class FlatTuple$/", "language": "C++", "kind": "class", "scope": "testing::internal", "scopeKind": "namespace"}, {"_type": "tag", "name": "FlatTupleBase", "path": "/home/kavia/workspace/code-generation/offline-to-do-list-manager-148807-148823/native_app/build/_deps/googletest-src/googletest/include/gtest/internal/gtest-internal.h", "pattern": "/^  explicit FlatTupleBase(FlatTupleConstructTag, Args&&... args)$/", "language": "C++", "kind": "function", "signature": "(FlatTupleConstructTag,Args &&...args)", "scope": "testing::internal::FlatTupleBase", "scopeKind": "struct"}, {"_type": "tag", "name": "FlatTupleBase", "path": "/home/kavia/workspace/code-generation/offline-to-do-list-manager-148807-148823/native_app/build/_deps/googletest-src/googletest/include/gtest/internal/gtest-internal.h", "pattern": "/^struct FlatTupleBase<FlatTuple<T...>, IndexSequence<Idx...>>$/", "language": "C++", "kind": "struct", "scope": "testing::internal", "scopeKind": "namespace"}, {"_type": "tag", "name": "FlatTupleConstructTag", "path": "/home/kavia/workspace/code-generation/offline-to-do-list-manager-148807-148823/native_app/build/_deps/googletest-src/googletest/include/gtest/internal/gtest-internal.h", "pattern": "/^struct FlatTupleConstructTag {};$/", "language": "C++", "kind": "struct", "scope": "testing::internal", "scopeKind": "namespace"}, {"_type": "tag", "name": "FlatTupleElemBase", "path": "/home/kavia/workspace/code-generation/offline-to-do-list-manager-148807-148823/native_app/build/_deps/googletest-src/googletest/include/gtest/internal/gtest-internal.h", "pattern": "/^  explicit FlatTupleElemBase(FlatTupleConstructTag, Arg&& t)$/", "language": "C++", "kind": "function", "signature": "(FlatTupleConstructTag,Arg && t)", "scope": "testing::internal::FlatTupleElemBase", "scopeKind": "struct"}, {"_type": "tag", "name": "FlatTupleElemBase", "path": "/home/kavia/workspace/code-generation/offline-to-do-list-manager-148807-148823/native_app/build/_deps/googletest-src/googletest/include/gtest/internal/gtest-internal.h", "pattern": "/^struct FlatTupleElemBase<FlatTuple<T...>, I> {$/", "language": "C++", "kind": "struct", "scope": "testing::internal", "scopeKind": "namespace"}, {"_type": "tag", "name": "Float", "path": "/home/kavia/workspace/code-generation/offline-to-do-list-manager-148807-148823/native_app/build/_deps/googletest-src/googletest/include/gtest/internal/gtest-internal.h", "pattern": "/^typedef FloatingPoint<float> Float;$/", "language": "C++", "typeref": "typename:FloatingPoint<float>", "kind": "typedef", "scope": "testing::internal", "scopeKind": "namespace"}, {"_type": "tag", "name": "FloatingPoint", "path": "/home/kavia/workspace/code-generation/offline-to-do-list-manager-148807-148823/native_app/build/_deps/googletest-src/googletest/include/gtest/internal/gtest-internal.h", "pattern": "/^  explicit FloatingPoint(const RawType& x) { u_.value_ = x; }$/", "language": "C++", "kind": "function", "signature": "(const RawType & x)", "scope": "testing::internal::FloatingPoint", "scopeKind": "class"}, {"_type": "tag", "name": "FloatingPoint", "path": "/home/kavia/workspace/code-generation/offline-to-do-list-manager-148807-148823/native_app/build/_deps/googletest-src/googletest/include/gtest/internal/gtest-internal.h", "pattern": "/^class FloatingPoint {$/", "language": "C++", "kind": "class", "scope": "testing::internal", "scopeKind": "namespace"}, {"_type": "tag", "name": "FloatingPointUnion", "path": "/home/kavia/workspace/code-generation/offline-to-do-list-manager-148807-148823/native_app/build/_deps/googletest-src/googletest/include/gtest/internal/gtest-internal.h", "pattern": "/^  union FloatingPointUnion {$/", "language": "C++", "kind": "union", "scope": "testing::internal::FloatingPoint", "scopeKind": "class"}, {"_type": "tag", "name": "GOOGLETEST_INCLUDE_GTEST_INTERNAL_GTEST_INTERNAL_H_", "path": "/home/kavia/workspace/code-generation/offline-to-do-list-manager-148807-148823/native_app/build/_deps/googletest-src/googletest/include/gtest/internal/gtest-internal.h", "pattern": "/^#define GOOGLETEST_INCLUDE_GTEST_INTERNAL_GTEST_INTERNAL_H_$/", "language": "C++", "kind": "macro"}, {"_type": "tag", "name": "GTEST_CONCAT_TOKEN_", "path": "/home/kavia/workspace/code-generation/offline-to-do-list-manager-148807-148823/native_app/build/_deps/googletest-src/googletest/include/gtest/internal/gtest-internal.h", "pattern": "/^#define GTEST_CONCAT_TOKEN_(/", "language": "C++", "kind": "macro", "signature": "(foo,bar)"}, {"_type": "tag", "name": "GTEST_CONCAT_TOKEN_IMPL_", "path": "/home/kavia/workspace/code-generation/offline-to-do-list-manager-148807-148823/native_app/build/_deps/googletest-src/googletest/include/gtest/internal/gtest-internal.h", "pattern": "/^#define GTEST_CONCAT_TOKEN_IMPL_(/", "language": "C++", "kind": "macro", "signature": "(foo,bar)"}, {"_type": "tag", "name": "GTEST_DISABLE_MSC_WARNINGS_POP_", "path": "/home/kavia/workspace/code-generation/offline-to-do-list-manager-148807-148823/native_app/build/_deps/googletest-src/googletest/include/gtest/internal/gtest-internal.h", "pattern": "/^GTEST_DISABLE_MSC_WARNINGS_POP_()  \\/\\/  4251$/", "language": "C++", "kind": "function", "signature": "() const", "scope": "testing::internal", "scopeKind": "namespace"}, {"_type": "tag", "name": "GTEST_EXCEPTION_TYPE_", "path": "/home/kavia/workspace/code-generation/offline-to-do-list-manager-148807-148823/native_app/build/_deps/googletest-src/googletest/include/gtest/internal/gtest-internal.h", "pattern": "/^#define GTEST_EXCEPTION_TYPE_(/", "language": "C++", "kind": "macro", "signature": "(e)"}, {"_type": "tag", "name": "GTEST_FATAL_FAILURE_", "path": "/home/kavia/workspace/code-generation/offline-to-do-list-manager-148807-148823/native_app/build/_deps/googletest-src/googletest/include/gtest/internal/gtest-internal.h", "pattern": "/^#define GTEST_FATAL_FAILURE_(/", "language": "C++", "kind": "macro", "signature": "(message)"}, {"_type": "tag", "name": "GTEST_MESSAGE_", "path": "/home/kavia/workspace/code-generation/offline-to-do-list-manager-148807-148823/native_app/build/_deps/googletest-src/googletest/include/gtest/internal/gtest-internal.h", "pattern": "/^#define GTEST_MESSAGE_(/", "language": "C++", "kind": "macro", "signature": "(message,result_type)"}, {"_type": "tag", "name": "GTEST_MESSAGE_AT_", "path": "/home/kavia/workspace/code-generation/offline-to-do-list-manager-148807-148823/native_app/build/_deps/googletest-src/googletest/include/gtest/internal/gtest-internal.h", "pattern": "/^#define GTEST_MESSAGE_AT_(/", "language": "C++", "kind": "macro", "signature": "(file,line,message,result_type)"}, {"_type": "tag", "name": "GTEST_NONFATAL_FAILURE_", "path": "/home/kavia/workspace/code-generation/offline-to-do-list-manager-148807-148823/native_app/build/_deps/googletest-src/googletest/include/gtest/internal/gtest-internal.h", "pattern": "/^#define GTEST_NONFATAL_FAILURE_(/", "language": "C++", "kind": "macro", "signature": "(message)"}, {"_type": "tag", "name": "GTEST_REMOVE_REFERENCE_AND_CONST_", "path": "/home/kavia/workspace/code-generation/offline-to-do-list-manager-148807-148823/native_app/build/_deps/googletest-src/googletest/include/gtest/internal/gtest-internal.h", "pattern": "/^#define GTEST_REMOVE_REFERENCE_AND_CONST_(/", "language": "C++", "kind": "macro", "signature": "(T)"}, {"_type": "tag", "name": "GTEST_SKIP_", "path": "/home/kavia/workspace/code-generation/offline-to-do-list-manager-148807-148823/native_app/build/_deps/googletest-src/googletest/include/gtest/internal/gtest-internal.h", "pattern": "/^#define GTEST_SKIP_(/", "language": "C++", "kind": "macro", "signature": "(message)"}, {"_type": "tag", "name": "GTEST_STRINGIFY_", "path": "/home/kavia/workspace/code-generation/offline-to-do-list-manager-148807-148823/native_app/build/_deps/googletest-src/googletest/include/gtest/internal/gtest-internal.h", "pattern": "/^#define GTEST_STRINGIFY_(/", "language": "C++", "kind": "macro", "signature": "(...)"}, {"_type": "tag", "name": "GTEST_STRINGIFY_HELPER_", "path": "/home/kavia/workspace/code-generation/offline-to-do-list-manager-148807-148823/native_app/build/_deps/googletest-src/googletest/include/gtest/internal/gtest-internal.h", "pattern": "/^#define GTEST_STRINGIFY_HELPER_(/", "language": "C++", "kind": "macro", "signature": "(name,...)"}, {"_type": "tag", "name": "GTEST_SUCCESS_", "path": "/home/kavia/workspace/code-generation/offline-to-do-list-manager-148807-148823/native_app/build/_deps/googletest-src/googletest/include/gtest/internal/gtest-internal.h", "pattern": "/^#define GTEST_SUCCESS_(/", "language": "C++", "kind": "macro", "signature": "(message)"}, {"_type": "tag", "name": "GTEST_SUPPRESS_UNREACHABLE_CODE_WARNING_BELOW_", "path": "/home/kavia/workspace/code-generation/offline-to-do-list-manager-148807-148823/native_app/build/_deps/googletest-src/googletest/include/gtest/internal/gtest-internal.h", "pattern": "/^#define GTEST_SUPPRESS_UNREACHABLE_CODE_WARNING_BELOW_(/", "language": "C++", "kind": "macro", "signature": "(statement)"}, {"_type": "tag", "name": "GTEST_TEST_", "path": "/home/kavia/workspace/code-generation/offline-to-do-list-manager-148807-148823/native_app/build/_deps/googletest-src/googletest/include/gtest/internal/gtest-internal.h", "pattern": "/^#define GTEST_TEST_(/", "language": "C++", "kind": "macro", "signature": "(test_suite_name,test_name,parent_class,parent_id)"}, {"_type": "tag", "name": "GTEST_TEST_ANY_THROW_", "path": "/home/kavia/workspace/code-generation/offline-to-do-list-manager-148807-148823/native_app/build/_deps/googletest-src/googletest/include/gtest/internal/gtest-internal.h", "pattern": "/^#define GTEST_TEST_ANY_THROW_(/", "language": "C++", "kind": "macro", "signature": "(statement,fail)"}, {"_type": "tag", "name": "GTEST_TEST_BOOLEAN_", "path": "/home/kavia/workspace/code-generation/offline-to-do-list-manager-148807-148823/native_app/build/_deps/googletest-src/googletest/include/gtest/internal/gtest-internal.h", "pattern": "/^#define GTEST_TEST_BOOLEAN_(/", "language": "C++", "kind": "macro", "signature": "(expression,text,actual,expected,fail)"}, {"_type": "tag", "name": "GTEST_TEST_CLASS_NAME_", "path": "/home/kavia/workspace/code-generation/offline-to-do-list-manager-148807-148823/native_app/build/_deps/googletest-src/googletest/include/gtest/internal/gtest-internal.h", "pattern": "/^#define GTEST_TEST_CLASS_NAME_(/", "language": "C++", "kind": "macro", "signature": "(test_suite_name,test_name)"}, {"_type": "tag", "name": "GTEST_TEST_NO_FATAL_FAILURE_", "path": "/home/kavia/workspace/code-generation/offline-to-do-list-manager-148807-148823/native_app/build/_deps/googletest-src/googletest/include/gtest/internal/gtest-internal.h", "pattern": "/^#define GTEST_TEST_NO_FATAL_FAILURE_(/", "language": "C++", "kind": "macro", "signature": "(statement,fail)"}, {"_type": "tag", "name": "GTEST_TEST_NO_THROW_", "path": "/home/kavia/workspace/code-generation/offline-to-do-list-manager-148807-148823/native_app/build/_deps/googletest-src/googletest/include/gtest/internal/gtest-internal.h", "pattern": "/^#define GTEST_TEST_NO_THROW_(/", "language": "C++", "kind": "macro", "signature": "(statement,fail)"}, {"_type": "tag", "name": "GTEST_TEST_NO_THROW_CATCH_STD_EXCEPTION_", "path": "/home/kavia/workspace/code-generation/offline-to-do-list-manager-148807-148823/native_app/build/_deps/googletest-src/googletest/include/gtest/internal/gtest-internal.h", "pattern": "/^#define GTEST_TEST_NO_THROW_CATCH_STD_EXCEPTION_(/", "language": "C++", "kind": "macro", "signature": "()"}, {"_type": "tag", "name": "GTEST_TEST_THROW_", "path": "/home/kavia/workspace/code-generation/offline-to-do-list-manager-148807-148823/native_app/build/_deps/googletest-src/googletest/include/gtest/internal/gtest-internal.h", "pattern": "/^#define GTEST_TEST_THROW_(/", "language": "C++", "kind": "macro", "signature": "(statement,expected_exception,fail)"}, {"_type": "tag", "name": "GTEST_TEST_THROW_CATCH_STD_EXCEPTION_", "path": "/home/kavia/workspace/code-generation/offline-to-do-list-manager-148807-148823/native_app/build/_deps/googletest-src/googletest/include/gtest/internal/gtest-internal.h", "pattern": "/^#define GTEST_TEST_THROW_CATCH_STD_EXCEPTION_(/", "language": "C++", "kind": "macro", "signature": "(statement,expected_exception)"}, {"_type": "tag", "name": "GenerateNames", "path": "/home/kavia/workspace/code-generation/offline-to-do-list-manager-148807-148823/native_app/build/_deps/googletest-src/googletest/include/gtest/internal/gtest-internal.h", "pattern": "/^std::vector<std::string> GenerateNames() {$/", "language": "C++", "typeref": "typename:std::vector<std::string>", "kind": "function", "signature": "()", "scope": "testing::internal", "scopeKind": "namespace"}, {"_type": "tag", "name": "GenerateNamesRecursively", "path": "/home/kavia/workspace/code-generation/offline-to-do-list-manager-148807-148823/native_app/build/_deps/googletest-src/googletest/include/gtest/internal/gtest-internal.h", "pattern": "/^void GenerateNamesRecursively(Types, std::vector<std::string>* result, int i) {$/", "language": "C++", "typeref": "typename:void", "kind": "function", "signature": "(Types,std::vector<std::string> * result,int i)", "scope": "testing::internal", "scopeKind": "namespace"}, {"_type": "tag", "name": "GenerateNamesRecursively", "path": "/home/kavia/workspace/code-generation/offline-to-do-list-manager-148807-148823/native_app/build/_deps/googletest-src/googletest/include/gtest/internal/gtest-internal.h", "pattern": "/^void GenerateNamesRecursively(internal::None, std::vector<std::string>*, int) {}$/", "language": "C++", "typeref": "typename:void", "kind": "function", "signature": "(internal::None,std::vector<std::string> *,int)", "scope": "testing::internal", "scopeKind": "namespace"}, {"_type": "tag", "name": "Get", "path": "/home/kavia/workspace/code-generation/offline-to-do-list-manager-148807-148823/native_app/build/_deps/googletest-src/googletest/include/gtest/internal/gtest-internal.h", "pattern": "/^  const typename ElemFromList<I, T...>::type& Get() const {$/", "language": "C++", "typeref": "typename:const typename ElemFromList<I,T...>::type &", "kind": "function", "signature": "() const", "scope": "testing::internal::FlatTupleBase", "scopeKind": "struct"}, {"_type": "tag", "name": "Get", "path": "/home/kavia/workspace/code-generation/offline-to-do-list-manager-148807-148823/native_app/build/_deps/googletest-src/googletest/include/gtest/internal/gtest-internal.h", "pattern": "/^  typename ElemFromList<I, T...>::type& Get() {$/", "language": "C++", "typeref": "typename:ElemFromList<I,T...>::type &", "kind": "function", "signature": "()", "scope": "testing::internal::FlatTupleBase", "scopeKind": "struct"}, {"_type": "tag", "name": "GetCodeLocation", "path": "/home/kavia/workspace/code-generation/offline-to-do-list-manager-148807-148823/native_app/build/_deps/googletest-src/googletest/include/gtest/internal/gtest-internal.h", "pattern": "/^  const CodeLocation& GetCodeLocation(const std::string& test_name) const {$/", "language": "C++", "typeref": "typename:const CodeLocation &", "kind": "function", "signature": "(const std::string & test_name) const", "scope": "testing::internal::TypedTestSuitePState", "scopeKind": "class"}, {"_type": "tag", "name": "GetName", "path": "/home/kavia/workspace/code-generation/offline-to-do-list-manager-148807-148823/native_app/build/_deps/googletest-src/googletest/include/gtest/internal/gtest-internal.h", "pattern": "/^  static std::string GetName(int i) {$/", "language": "C++", "typeref": "typename:std::string", "kind": "function", "signature": "(int i)", "scope": "testing::internal::DefaultNameGenerator", "scopeKind": "struct"}, {"_type": "tag", "name": "GetNotDefaultOrNull", "path": "/home/kavia/workspace/code-generation/offline-to-do-list-manager-148807-148823/native_app/build/_deps/googletest-src/googletest/include/gtest/internal/gtest-internal.h", "pattern": "/^inline SetUpTearDownSuiteFuncType GetNotDefaultOrNull($/", "language": "C++", "typeref": "typename:SetUpTearDownSuiteFuncType", "kind": "function", "signature": "(SetUpTearDownSuiteFuncType a,SetUpTearDownSuiteFuncType def)", "scope": "testing::internal", "scopeKind": "namespace"}, {"_type": "tag", "name": "GetPrefixUntilComma", "path": "/home/kavia/workspace/code-generation/offline-to-do-list-manager-148807-148823/native_app/build/_deps/googletest-src/googletest/include/gtest/internal/gtest-internal.h", "pattern": "/^inline std::string GetPrefixUntilComma(const char* str) {$/", "language": "C++", "typeref": "typename:std::string", "kind": "function", "signature": "(const char * str)", "scope": "testing::internal", "scopeKind": "namespace"}, {"_type": "tag", "name": "GetSetUpCaseOrSuite", "path": "/home/kavia/workspace/code-generation/offline-to-do-list-manager-148807-148823/native_app/build/_deps/googletest-src/googletest/include/gtest/internal/gtest-internal.h", "pattern": "/^  static SetUpTearDownSuiteFuncType GetSetUpCaseOrSuite(const char* filename,$/", "language": "C++", "typeref": "typename:SetUpTearDownSuiteFuncType", "kind": "function", "signature": "(const char * filename,int line_num)", "scope": "testing::internal::SuiteApiResolver", "scopeKind": "struct"}, {"_type": "tag", "name": "GetTearDownCaseOrSuite", "path": "/home/kavia/workspace/code-generation/offline-to-do-list-manager-148807-148823/native_app/build/_deps/googletest-src/googletest/include/gtest/internal/gtest-internal.h", "pattern": "/^  static SetUpTearDownSuiteFuncType GetTearDownCaseOrSuite(const char* filename,$/", "language": "C++", "typeref": "typename:SetUpTearDownSuiteFuncType", "kind": "function", "signature": "(const char * filename,int line_num)", "scope": "testing::internal::SuiteApiResolver", "scopeKind": "struct"}, {"_type": "tag", "name": "proto2", "path": "/home/kavia/workspace/code-generation/offline-to-do-list-manager-148807-148823/native_app/build/_deps/googletest-src/googletest/include/gtest/internal/gtest-internal.h", "pattern": "/^namespace proto2 {$/", "language": "C++", "kind": "namespace"}], "hash": "3e8826df5ff65a6ae6ff319f603b6079", "format-version": 4, "code-base-name": "native_app", "filename": "native_app/build/_deps/googletest-src/googletest/include/gtest/internal/gtest-internal.h", "revision_history": [{"606": ""}]}